whatsapp_chatgpt_python/__init__.py
whatsapp_chatgpt_python/bot.py
whatsapp_chatgpt_python/config.py
whatsapp_chatgpt_python/logger.py
whatsapp_chatgpt_python/models.py
whatsapp_chatgpt_python/notification.py
whatsapp_chatgpt_python/handlers/__init__.py
whatsapp_chatgpt_python/handlers/audio.py
whatsapp_chatgpt_python/handlers/base.py
whatsapp_chatgpt_python/handlers/contact.py
whatsapp_chatgpt_python/handlers/document.py
whatsapp_chatgpt_python/handlers/image.py
whatsapp_chatgpt_python/handlers/location.py
whatsapp_chatgpt_python/handlers/poll.py
whatsapp_chatgpt_python/handlers/registry.py
whatsapp_chatgpt_python/handlers/text.py
whatsapp_chatgpt_python/handlers/video.py
whatsapp_chatgpt_python/middleware/__init__.py
whatsapp_chatgpt_python/middleware/base.py
whatsapp_chatgpt_python/middleware/manager.py
whatsapp_chatgpt_python/utils/__init__.py
whatsapp_chatgpt_python/utils/conversation.py
whatsapp_chatgpt_python/utils/media.py
whatsapp_chatgpt_python/utils/router.py
whatsapp_chatgpt_python-1.0.0.dist-info/LICENSE
whatsapp_chatgpt_python-1.0.0.dist-info/METADATA
whatsapp_chatgpt_python-1.0.0.dist-info/WHEEL
whatsapp_chatgpt_python-1.0.0.dist-info/top_level.txt
whatsapp_chatgpt_python-1.0.0.dist-info/RECORD
