Metadata-Version: 2.2
Name: whatsapp-chatgpt-python
Version: 1.0.0
Summary: A modern WhatsApp bot library with OpenAI GPT integration on Python
Home-page: https://github.com/green-api/whatsapp-chatgpt-python
Author: GREEN-API
Author-email: support@green-api.com
License: MIT
Classifier: Programming Language :: Python :: 3
Classifier: License :: OSI Approved :: MIT License
Classifier: Operating System :: OS Independent
Requires-Python: >=3.7
License-File: LICENSE
Requires-Dist: whatsapp-chatbot-python>=0.9.6
Requires-Dist: openai>=1.66.3
Requires-Dist: requests>=2.32.3
Dynamic: author
Dynamic: author-email
Dynamic: classifier
Dynamic: description
Dynamic: description-content-type
Dynamic: home-page
Dynamic: license
Dynamic: requires-dist
Dynamic: requires-python
Dynamic: summary
